{
	"uniqueUsers": 325,
	"playerTimes": [{"id":28878129,"timeOn":182184,"username":"Azrellie"},{"id":1158314247,"timeOn":928252,"username":"DisquaIlification"},{"id":1583616335,"timeOn":411863,"username":"epicisawesome12"},{"id":544627013,"timeOn":318703,"username":"NothingMore_GoAway"},{"id":274724369,"timeOn":281921,"username":"TalkingTom2300"},{"id":155840386,"timeOn":134810,"username":"cyclonicchris"},{"id":4458675573,"timeOn":111159,"username":"chinaaltnumber100M"},{"id":78251197,"timeOn":93157,"username":"davygravy10"},{"id":5251603301,"timeOn":82421,"username":"DeccanTrapsAlt"},{"id":1323853299,"timeOn":80248,"username":"SillySteve9"},{"id":829343471,"timeOn":65466,"username":"MatthewEpicPlayer09"},{"id":2337749874,"timeOn":52500,"username":"hunor2511"},{"id":132286399,"timeOn":44313,"username":"ikergamers"},{"id":4251569640,"timeOn":41446,"username":"tibbe_bot2"},{"id":51777447,"timeOn":40722,"username":"nclearsphinx"},{"id":5239116733,"timeOn":39361,"username":"JTdinokid2"},{"id":76882833,"timeOn":36855,"username":"baconatorboy95"},{"id":4252471790,"timeOn":35731,"username":"SpeedCuber_0"},{"id":1696037199,"timeOn":34784,"username":"Jacob_Thestormchaser"},{"id":3883123712,"timeOn":33097,"username":"Joe_Alt19"},{"id":42104764,"timeOn":33084,"username":"NoahToups"},{"id":358166108,"timeOn":32352,"username":"MrLukasMan"},{"id":148115946,"timeOn":30322,"username":"SinsMachine"},{"id":887689610,"timeOn":29500,"username":"nollypolly111"},{"id":4052151085,"timeOn":29430,"username":"CORE3020210"},{"id":161147759,"timeOn":28333,"username":"OliverEspelid"},{"id":90491867,"timeOn":26255,"username":"elibasker"},{"id":2023496830,"timeOn":25454,"username":"comodo_gamiz"},{"id":5214144648,"timeOn":24650,"username":"Thund3r_Lightning"},{"id":2529777835,"timeOn":23508,"username":"DisasterGuy2142"},{"id":1456585262,"timeOn":23390,"username":"Hunor251"},{"id":87053793,"timeOn":21360,"username":"paulmaestas"},{"id":1052406956,"timeOn":19935,"username":"perictione2001"},{"id":303118411,"timeOn":19476,"username":"CollinHD1234"},{"id":2635422323,"timeOn":18786,"username":"JohnPlays1500"},{"id":1562963095,"timeOn":17996,"username":"nighlastu"},{"id":196250982,"timeOn":16418,"username":"Ayaz2345"},{"id":3590835677,"timeOn":16101,"username":"Rubin_qwq2"},{"id":116599866,"timeOn":14558,"username":"pyrodupe"},{"id":1973388392,"timeOn":13585,"username":"LankyyyBoisia"},{"id":320125499,"timeOn":13475,"username":"josiahevan1"},{"id":3851534892,"timeOn":13384,"username":"Ght2400"},{"id":3582871812,"timeOn":13271,"username":"Teodor_273"},{"id":1724334229,"timeOn":13067,"username":"Cartoondog2p"},{"id":3274841926,"timeOn":12491,"username":"ProfessorXJ2013"},{"id":4989709620,"timeOn":12115,"username":"Ea12065"},{"id":3219282344,"timeOn":11438,"username":"play00_04"},{"id":5567831712,"timeOn":11016,"username":"crazywitit200"},{"id":4527966362,"timeOn":10752,"username":"1Milewidetornadopls"},{"id":1566174930,"timeOn":10566,"username":"mimicito34"},{"id":1932221746,"timeOn":10141,"username":"f5turtle"},{"id":365410019,"timeOn":9937,"username":"xxxreil"},{"id":326774294,"timeOn":9894,"username":"SiriwayOfficial"},{"id":229664833,"timeOn":9018,"username":"whethersoldacc12"},{"id":4226393187,"timeOn":8999,"username":"siryzm1"},{"id":1026189900,"timeOn":8335,"username":"Sentient_Portapotty"},{"id":4852513794,"timeOn":8225,"username":"bloxfruitsplayer5001"},{"id":1593059309,"timeOn":8183,"username":"bfbissool"},{"id":3002599048,"timeOn":7844,"username":"EEEEEEEEEEEE_1232"},{"id":25618436,"timeOn":7468,"username":"weedestroyer1235"},{"id":65585355,"timeOn":7322,"username":"monsterquest17"},{"id":1323598002,"timeOn":7285,"username":"ShadowWolf20203"},{"id":1709494937,"timeOn":6995,"username":"RoGinRoy"},{"id":4296159606,"timeOn":6927,"username":"sorry_dudeIdied"},{"id":1691500616,"timeOn":6849,"username":"percyandpeter"},{"id":2387638563,"timeOn":6634,"username":"DavidYueYaya"},{"id":2600665708,"timeOn":6522,"username":"GMOBananas"},{"id":4114066931,"timeOn":6309,"username":"tachno_cats"},{"id":4879750054,"timeOn":6303,"username":"SmiledLemuriphone"},{"id":411086528,"timeOn":6242,"username":"RaioMiguel111011"},{"id":4763734049,"timeOn":6225,"username":"sedfghjklkjhgfd"},{"id":2794378206,"timeOn":6087,"username":"gianniplay99"},{"id":479722357,"timeOn":6072,"username":"Ideaful"},{"id":547125815,"timeOn":5982,"username":"BewereOfGafa"},{"id":1961021642,"timeOn":5970,"username":"radarbsm"},{"id":4093173066,"timeOn":5917,"username":"bob1264972"},{"id":1869269680,"timeOn":5905,"username":"Jimmy_LovesHam"},{"id":286965437,"timeOn":5904,"username":"CAMILO_OSIRIS"},{"id":71131101,"timeOn":5629,"username":"Krge"},{"id":1118582946,"timeOn":5420,"username":"cookiesneeze05"},{"id":42155457,"timeOn":5323,"username":"dragonballzfan98"},{"id":2634997924,"timeOn":5124,"username":"natstar1984"},{"id":1309423537,"timeOn":4695,"username":"ancan24567"},{"id":3309150088,"timeOn":4362,"username":"frendphaddin"},{"id":1240831890,"timeOn":3823,"username":"Whitney1963Houston"},{"id":5467141852,"timeOn":3654,"username":"Uohhhhhh5"},{"id":860134184,"timeOn":3650,"username":"Falaeh"},{"id":1206310505,"timeOn":3609,"username":"robox7002"},{"id":219010326,"timeOn":3470,"username":"IAmTheMordecaiSimp"},{"id":3321317059,"timeOn":3312,"username":"Erdoganyarrak"},{"id":1351634690,"timeOn":3164,"username":"talleresatr"},{"id":1249675019,"timeOn":3158,"username":"akanabahii"},{"id":3475009922,"timeOn":3125,"username":"Openone33"},{"id":4033701676,"timeOn":2988,"username":"ThatTyphoonAlt4"},{"id":1495991196,"timeOn":2943,"username":"fourblocks7"},{"id":1330762303,"timeOn":2909,"username":"MjKam1315513"},{"id":552573555,"timeOn":2871,"username":"0rig1na1y"},{"id":1909114056,"timeOn":2834,"username":"EastwoodHunter"},{"id":1691862788,"timeOn":2455,"username":"imaproinpiggy4"},{"id":189624867,"timeOn":2411,"username":"jtb2011"}]
}